mcp_hn/__init__.py
mcp_hn/hn.py
mcp_hn/server.py
mcp_hn-0.1.0.dist-info/METADATA
mcp_hn-0.1.0.dist-info/WHEEL
mcp_hn-0.1.0.dist-info/entry_points.txt
mcp_hn-0.1.0.dist-info/RECORD
