Metadata-Version: 2.3
Name: mcp-hn
Version: 0.1.0
Summary: MCP Server for Hacker News
Author-email: Ricky <ricky.ediga@gmail.com>
Requires-Python: >=3.12
Requires-Dist: mcp[cli]>=1.1.2
Requires-Dist: requests>=2.32.3
